{"cameraMode":{"drawMode":0,"name":"Shaded","section":"Shading Mode"},"sceneLighting":false,"audioPlay":false,"sceneViewState":{"m_AlwaysRefresh":false,"showFog":true,"showSkybox":false,"showFlares":true,"showImageEffects":true,"showParticleSystems":true,"showVisualEffectGraphs":true,"m_FxEnabled":true},"in2DMode":false,"pivot":{"x":2.345421075820923,"y":3.610671281814575,"z":0.7289108037948608},"rotation":{"x":-0.22908098995685578,"y":0.7372925281524658,"z":-0.30204394459724429,"w":-0.5591976046562195},"size":1.7320507764816285,"orthographic":false}